[
    {
      "state": "AK",
      "Democratic": 445,
      "Republican": 17,
      "total": 462,
      "topic_breakdown": {
        "abortion": {
          "Democratic": 1,
          "Republican": 0,
          "total": 1
        },
        "capitol": {
          "Democratic": 8,
          "Republican": 1,
          "total": 9
        },
        "climate": {
          "Democratic": 10,
          "Republican": 0,
          "total": 10
        },
        "covid": {
          "Democratic": 383,
          "Republican": 16,
          "total": 399
        },
        "gun": {
          "Democratic": 5,
          "Republican": 0,
          "total": 5
        },
        "immigra": {
          "Democratic": 1,
          "Republican": 0,
          "total": 1
        },
        "rights": {
          "Democratic": 37,
          "Republican": 0,
          "total": 37
        }
      },
      "legislator_breakdown": {
        "abortion": {
          "Democratic": 1,
          "Republican": 0,
          "total": 1
        },
        "capitol": {
          "Democratic": 8,
          "Republican": 1,
          "total": 9
        },
        "climate": {
          "Democratic": 10,
          "Republican": 0,
          "total": 10
        },
        "covid": {
          "Democratic": 383,
          "Republican": 16,
          "total": 399
        },
        "gun": {
          "Democratic": 5,
          "Republican": 0,
          "total": 5
        },
        "immigra": {
          "Democratic": 1,
          "Republican": 0,
          "total": 1
        },
        "rights": {
          "Democratic": 37,
          "Republican": 0,
          "total": 37
        }
      }
    },
    {
      "state": "AL",
      "Democratic": 264,
      "Republican": 1376,
      "total": 1640,
      "topic_breakdown": {
        "abortion": {
          "Democratic": 4,
          "Republican": 122,
          "total": 126
        },
        "capitol": {
          "Democratic": 7,
          "Republican": 28,
          "total": 35
        },
        "climate": {
          "Democratic": 1,
          "Republican": 25,
          "total": 26
        },
        "covid": {
          "Democratic": 206,
          "Republican": 929,
          "total": 1135
        },
        "gun": {
          "Democratic": 16,
          "Republican": 128,
          "total": 144
        },
        "immigra": {
          "Democratic": 1,
          "Republican": 69,
          "total": 70
        },
        "rights": {
          "Democratic": 29,
          "Republican": 75,
          "total": 104
        }
      },
      "legislator_breakdown": {
        "abortion": {
          "Democratic": 4,
          "Republican": 122,
          "total": 126
        },
        "capitol": {
          "Democratic": 7,
          "Republican": 28,
          "total": 35
        },
        "climate": {
          "Democratic": 1,
          "Republican": 25,
          "total": 26
        },
        "covid": {
          "Democratic": 206,
          "Republican": 929,
          "total": 1135
        },
        "gun": {
          "Democratic": 16,
          "Republican": 128,
          "total": 144
        },
        "immigra": {
          "Democratic": 1,
          "Republican": 69,
          "total": 70
        },
        "rights": {
          "Democratic": 29,
          "Republican": 75,
          "total": 104
        }
      }
    },
    {
      "state": "AR",
      "Democratic": 3090,
      "Republican": 2297,
      "total": 5387,
      "topic_breakdown": {
        "abortion": {
          "Democratic": 28,
          "Republican": 541,
          "total": 569
        },
        "capitol": {
          "Democratic": 29,
          "Republican": 30,
          "total": 59
        },
        "climate": {
          "Democratic": 11,
          "Republican": 18,
          "total": 29
        },
        "covid": {
          "Democratic": 2775,
          "Republican": 1381,
          "total": 4156
        },
        "gun": {
          "Democratic": 65,
          "Republican": 134,
          "total": 199
        },
        "immigra": {
          "Democratic": 17,
          "Republican": 31,
          "total": 48
        },
        "rights": {
          "Democratic": 165,
          "Republican": 162,
          "total": 327
        }
      },
      "legislator_breakdown": {
        "abortion": {
          "Democratic": 28,
          "Republican": 541,
          "total": 569
        },
        "capitol": {
          "Democratic": 29,
          "Republican": 30,
          "total": 59
        },
        "climate": {
          "Democratic": 11,
          "Republican": 18,
          "total": 29
        },
        "covid": {
          "Democratic": 2775,
          "Republican": 1381,
          "total": 4156
        },
        "gun": {
          "Democratic": 65,
          "Republican": 134,
          "total": 199
        },
        "immigra": {
          "Democratic": 17,
          "Republican": 31,
          "total": 48
        },
        "rights": {
          "Democratic": 165,
          "Republican": 162,
          "total": 327
        }
      }
    },
    {
      "state": "AZ",
      "Democratic": 11767,
      "Republican": 4954,
      "total": 16721,
      "topic_breakdown": {
        "abortion": {
          "Democratic": 754,
          "Republican": 590,
          "total": 1344
        },
        "capitol": {
          "Democratic": 461,
          "Republican": 272,
          "total": 733
        },
        "climate": {
          "Democratic": 643,
          "Republican": 114,
          "total": 757
        },
        "covid": {
          "Democratic": 7582,
          "Republican": 2534,
          "total": 10116
        },
        "gun": {
          "Democratic": 589,
          "Republican": 554,
          "total": 1143
        },
        "immigra": {
          "Democratic": 398,
          "Republican": 487,
          "total": 885
        },
        "rights": {
          "Democratic": 1340,
          "Republican": 403,
          "total": 1743
        }
      },
      "legislator_breakdown": {
        "abortion": {
          "Democratic": 754,
          "Republican": 590,
          "total": 1344
        },
        "capitol": {
          "Democratic": 461,
          "Republican": 272,
          "total": 733
        },
        "climate": {
          "Democratic": 643,
          "Republican": 114,
          "total": 757
        },
        "covid": {
          "Democratic": 7582,
          "Republican": 2534,
          "total": 10116
        },
        "gun": {
          "Democratic": 589,
          "Republican": 554,
          "total": 1143
        },
        "immigra": {
          "Democratic": 398,
          "Republican": 487,
          "total": 885
        },
        "rights": {
          "Democratic": 1340,
          "Republican": 403,
          "total": 1743
        }
      }
    },
    {
      "state": "CA",
      "Democratic": 15012,
      "Republican": 1680,
      "total": 16692,
      "topic_breakdown": {
        "abortion": {
          "Democratic": 167,
          "Republican": 0,
          "total": 167
        },
        "capitol": {
          "Democratic": 70,
          "Republican": 25,
          "total": 95
        },
        "climate": {
          "Democratic": 940,
          "Republican": 69,
          "total": 1009
        },
        "covid": {
          "Democratic": 11709,
          "Republican": 1446,
          "total": 13155
        },
        "gun": {
          "Democratic": 703,
          "Republican": 28,
          "total": 731
        },
        "immigra": {
          "Democratic": 480,
          "Republican": 17,
          "total": 497
        },
        "rights": {
          "Democratic": 943,
          "Republican": 95,
          "total": 1038
        }
      },
      "legislator_breakdown": {
        "abortion": {
          "Democratic": 167,
          "Republican": 0,
          "total": 167
        },
        "capitol": {
          "Democratic": 70,
          "Republican": 25,
          "total": 95
        },
        "climate": {
          "Democratic": 940,
          "Republican": 69,
          "total": 1009
        },
        "covid": {
          "Democratic": 11709,
          "Republican": 1446,
          "total": 13155
        },
        "gun": {
          "Democratic": 703,
          "Republican": 28,
          "total": 731
        },
        "immigra": {
          "Democratic": 480,
          "Republican": 17,
          "total": 497
        },
        "rights": {
          "Democratic": 943,
          "Republican": 95,
          "total": 1038
        }
      }
    },
    {
      "state": "CO",
      "Democratic": 4109,
      "Republican": 464,
      "total": 4573,
      "topic_breakdown": {
        "abortion": {
          "Democratic": 87,
          "Republican": 22,
          "total": 109
        },
        "capitol": {
          "Democratic": 155,
          "Republican": 95,
          "total": 250
        },
        "climate": {
          "Democratic": 392,
          "Republican": 10,
          "total": 402
        },
        "covid": {
          "Democratic": 2455,
          "Republican": 244,
          "total": 2699
        },
        "gun": {
          "Democratic": 483,
          "Republican": 44,
          "total": 527
        },
        "immigra": {
          "Democratic": 141,
          "Republican": 14,
          "total": 155
        },
        "rights": {
          "Democratic": 396,
          "Republican": 35,
          "total": 431
        }
      },
      "legislator_breakdown": {
        "abortion": {
          "Democratic": 87,
          "Republican": 22,
          "total": 109
        },
        "capitol": {
          "Democratic": 155,
          "Republican": 95,
          "total": 250
        },
        "climate": {
          "Democratic": 392,
          "Republican": 10,
          "total": 402
        },
        "covid": {
          "Democratic": 2455,
          "Republican": 244,
          "total": 2699
        },
        "gun": {
          "Democratic": 483,
          "Republican": 44,
          "total": 527
        },
        "immigra": {
          "Democratic": 141,
          "Republican": 14,
          "total": 155
        },
        "rights": {
          "Democratic": 396,
          "Republican": 35,
          "total": 431
        }
      }
    },
    {
      "state": "CT",
      "Democratic": 2299,
      "Republican": 785,
      "total": 3084,
      "topic_breakdown": {
        "abortion": {
          "Democratic": 16,
          "Republican": 0,
          "total": 16
        },
        "capitol": {
          "Democratic": 36,
          "Republican": 14,
          "total": 50
        },
        "climate": {
          "Democratic": 120,
          "Republican": 5,
          "total": 125
        },
        "covid": {
          "Democratic": 1773,
          "Republican": 737,
          "total": 2510
        },
        "gun": {
          "Democratic": 142,
          "Republican": 7,
          "total": 149
        },
        "immigra": {
          "Democratic": 48,
          "Republican": 1,
          "total": 49
        },
        "rights": {
          "Democratic": 164,
          "Republican": 21,
          "total": 185
        }
      },
      "legislator_breakdown": {
        "abortion": {
          "Democratic": 16,
          "Republican": 0,
          "total": 16
        },
        "capitol": {
          "Democratic": 36,
          "Republican": 14,
          "total": 50
        },
        "climate": {
          "Democratic": 120,
          "Republican": 5,
          "total": 125
        },
        "covid": {
          "Democratic": 1773,
          "Republican": 737,
          "total": 2510
        },
        "gun": {
          "Democratic": 142,
          "Republican": 7,
          "total": 149
        },
        "immigra": {
          "Democratic": 48,
          "Republican": 1,
          "total": 49
        },
        "rights": {
          "Democratic": 164,
          "Republican": 21,
          "total": 185
        }
      }
    },
    {
      "state": "DE",
      "Democratic": 1366,
      "Republican": 8,
      "total": 1374,
      "topic_breakdown": {
        "abortion": {
          "Democratic": 44,
          "Republican": 0,
          "total": 44
        },
        "capitol": {
          "Democratic": 61,
          "Republican": 0,
          "total": 61
        },
        "climate": {
          "Democratic": 25,
          "Republican": 0,
          "total": 25
        },
        "covid": {
          "Democratic": 997,
          "Republican": 7,
          "total": 1004
        },
        "gun": {
          "Democratic": 116,
          "Republican": 1,
          "total": 117
        },
        "immigra": {
          "Democratic": 17,
          "Republican": 0,
          "total": 17
        },
        "rights": {
          "Democratic": 106,
          "Republican": 0,
          "total": 106
        }
      },
      "legislator_breakdown": {
        "abortion": {
          "Democratic": 44,
          "Republican": 0,
          "total": 44
        },
        "capitol": {
          "Democratic": 61,
          "Republican": 0,
          "total": 61
        },
        "climate": {
          "Democratic": 25,
          "Republican": 0,
          "total": 25
        },
        "covid": {
          "Democratic": 997,
          "Republican": 7,
          "total": 1004
        },
        "gun": {
          "Democratic": 116,
          "Republican": 1,
          "total": 117
        },
        "immigra": {
          "Democratic": 17,
          "Republican": 0,
          "total": 17
        },
        "rights": {
          "Democratic": 106,
          "Republican": 0,
          "total": 106
        }
      }
    },
    {
      "state": "FL",
      "Democratic": 7407,
      "Republican": 3164,
      "total": 10571,
      "topic_breakdown": {
        "abortion": {
          "Democratic": 160,
          "Republican": 40,
          "total": 200
        },
        "capitol": {
          "Democratic": 137,
          "Republican": 46,
          "total": 183
        },
        "climate": {
          "Democratic": 183,
          "Republican": 101,
          "total": 284
        },
        "covid": {
          "Democratic": 5645,
          "Republican": 2525,
          "total": 8170
        },
        "gun": {
          "Democratic": 493,
          "Republican": 109,
          "total": 602
        },
        "immigra": {
          "Democratic": 124,
          "Republican": 118,
          "total": 242
        },
        "rights": {
          "Democratic": 665,
          "Republican": 225,
          "total": 890
        }
      },
      "legislator_breakdown": {
        "abortion": {
          "Democratic": 160,
          "Republican": 40,
          "total": 200
        },
        "capitol": {
          "Democratic": 137,
          "Republican": 46,
          "total": 183
        },
        "climate": {
          "Democratic": 183,
          "Republican": 101,
          "total": 284
        },
        "covid": {
          "Democratic": 5645,
          "Republican": 2525,
          "total": 8170
        },
        "gun": {
          "Democratic": 493,
          "Republican": 109,
          "total": 602
        },
        "immigra": {
          "Democratic": 124,
          "Republican": 118,
          "total": 242
        },
        "rights": {
          "Democratic": 665,
          "Republican": 225,
          "total": 890
        }
      }
    },
    {
      "state": "GA",
      "Democratic": 5422,
      "Republican": 915,
      "total": 6337,
      "topic_breakdown": {
        "abortion": {
          "Democratic": 181,
          "Republican": 61,
          "total": 242
        },
        "capitol": {
          "Democratic": 212,
          "Republican": 25,
          "total": 237
        },
        "climate": {
          "Democratic": 58,
          "Republican": 13,
          "total": 71
        },
        "covid": {
          "Democratic": 3781,
          "Republican": 694,
          "total": 4475
        },
        "gun": {
          "Democratic": 329,
          "Republican": 23,
          "total": 352
        },
        "immigra": {
          "Democratic": 113,
          "Republican": 22,
          "total": 135
        },
        "rights": {
          "Democratic": 748,
          "Republican": 77,
          "total": 825
        }
      },
      "legislator_breakdown": {
        "abortion": {
          "Democratic": 181,
          "Republican": 61,
          "total": 242
        },
        "capitol": {
          "Democratic": 212,
          "Republican": 25,
          "total": 237
        },
        "climate": {
          "Democratic": 58,
          "Republican": 13,
          "total": 71
        },
        "covid": {
          "Democratic": 3781,
          "Republican": 694,
          "total": 4475
        },
        "gun": {
          "Democratic": 329,
          "Republican": 23,
          "total": 352
        },
        "immigra": {
          "Democratic": 113,
          "Republican": 22,
          "total": 135
        },
        "rights": {
          "Democratic": 748,
          "Republican": 77,
          "total": 825
        }
      }
    },
    {
      "state": "HI",
      "Democratic": 1027,
      "Republican": 126,
      "total": 1153,
      "topic_breakdown": {
        "abortion": {
          "Democratic": 2,
          "Republican": 1,
          "total": 3
        },
        "capitol": {
          "Democratic": 28,
          "Republican": 0,
          "total": 28
        },
        "climate": {
          "Democratic": 42,
          "Republican": 0,
          "total": 42
        },
        "covid": {
          "Democratic": 897,
          "Republican": 122,
          "total": 1019
        },
        "gun": {
          "Democratic": 19,
          "Republican": 1,
          "total": 20
        },
        "immigra": {
          "Democratic": 7,
          "Republican": 0,
          "total": 7
        },
        "rights": {
          "Democratic": 32,
          "Republican": 2,
          "total": 34
        }
      },
      "legislator_breakdown": {
        "abortion": {
          "Democratic": 2,
          "Republican": 1,
          "total": 3
        },
        "capitol": {
          "Democratic": 28,
          "Republican": 0,
          "total": 28
        },
        "climate": {
          "Democratic": 42,
          "Republican": 0,
          "total": 42
        },
        "covid": {
          "Democratic": 897,
          "Republican": 122,
          "total": 1019
        },
        "gun": {
          "Democratic": 19,
          "Republican": 1,
          "total": 20
        },
        "immigra": {
          "Democratic": 7,
          "Republican": 0,
          "total": 7
        },
        "rights": {
          "Democratic": 32,
          "Republican": 2,
          "total": 34
        }
      }
    },
    {
      "state": "IA",
      "Democratic": 4735,
      "Republican": 330,
      "total": 5065,
      "topic_breakdown": {
        "abortion": {
          "Democratic": 63,
          "Republican": 14,
          "total": 77
        },
        "capitol": {
          "Democratic": 106,
          "Republican": 2,
          "total": 108
        },
        "climate": {
          "Democratic": 467,
          "Republican": 8,
          "total": 475
        },
        "covid": {
          "Democratic": 3649,
          "Republican": 248,
          "total": 3897
        },
        "gun": {
          "Democratic": 124,
          "Republican": 14,
          "total": 138
        },
        "immigra": {
          "Democratic": 24,
          "Republican": 17,
          "total": 41
        },
        "rights": {
          "Democratic": 302,
          "Republican": 27,
          "total": 329
        }
      },
      "legislator_breakdown": {
        "abortion": {
          "Democratic": 63,
          "Republican": 14,
          "total": 77
        },
        "capitol": {
          "Democratic": 106,
          "Republican": 2,
          "total": 108
        },
        "climate": {
          "Democratic": 467,
          "Republican": 8,
          "total": 475
        },
        "covid": {
          "Democratic": 3649,
          "Republican": 248,
          "total": 3897
        },
        "gun": {
          "Democratic": 124,
          "Republican": 14,
          "total": 138
        },
        "immigra": {
          "Democratic": 24,
          "Republican": 17,
          "total": 41
        },
        "rights": {
          "Democratic": 302,
          "Republican": 27,
          "total": 329
        }
      }
    },
    {
      "state": "ID",
      "Democratic": 473,
      "Republican": 171,
      "total": 644,
      "topic_breakdown": {
        "abortion": {
          "Democratic": 10,
          "Republican": 1,
          "total": 11
        },
        "capitol": {
          "Democratic": 44,
          "Republican": 7,
          "total": 51
        },
        "climate": {
          "Democratic": 20,
          "Republican": 3,
          "total": 23
        },
        "covid": {
          "Democratic": 299,
          "Republican": 136,
          "total": 435
        },
        "gun": {
          "Democratic": 44,
          "Republican": 7,
          "total": 51
        },
        "immigra": {
          "Democratic": 6,
          "Republican": 2,
          "total": 8
        },
        "rights": {
          "Democratic": 50,
          "Republican": 15,
          "total": 65
        }
      },
      "legislator_breakdown": {
        "abortion": {
          "Democratic": 10,
          "Republican": 1,
          "total": 11
        },
        "capitol": {
          "Democratic": 44,
          "Republican": 7,
          "total": 51
        },
        "climate": {
          "Democratic": 20,
          "Republican": 3,
          "total": 23
        },
        "covid": {
          "Democratic": 299,
          "Republican": 136,
          "total": 435
        },
        "gun": {
          "Democratic": 44,
          "Republican": 7,
          "total": 51
        },
        "immigra": {
          "Democratic": 6,
          "Republican": 2,
          "total": 8
        },
        "rights": {
          "Democratic": 50,
          "Republican": 15,
          "total": 65
        }
      }
    },
    {
      "state": "IL",
      "Democratic": 2979,
      "Republican": 608,
      "total": 3587,
      "topic_breakdown": {
        "abortion": {
          "Democratic": 34,
          "Republican": 31,
          "total": 65
        },
        "capitol": {
          "Democratic": 19,
          "Republican": 19,
          "total": 38
        },
        "climate": {
          "Democratic": 234,
          "Republican": 13,
          "total": 247
        },
        "covid": {
          "Democratic": 2356,
          "Republican": 464,
          "total": 2820
        },
        "gun": {
          "Democratic": 87,
          "Republican": 25,
          "total": 112
        },
        "immigra": {
          "Democratic": 62,
          "Republican": 14,
          "total": 76
        },
        "rights": {
          "Democratic": 187,
          "Republican": 42,
          "total": 229
        }
      },
      "legislator_breakdown": {
        "abortion": {
          "Democratic": 34,
          "Republican": 31,
          "total": 65
        },
        "capitol": {
          "Democratic": 19,
          "Republican": 19,
          "total": 38
        },
        "climate": {
          "Democratic": 234,
          "Republican": 13,
          "total": 247
        },
        "covid": {
          "Democratic": 2356,
          "Republican": 464,
          "total": 2820
        },
        "gun": {
          "Democratic": 87,
          "Republican": 25,
          "total": 112
        },
        "immigra": {
          "Democratic": 62,
          "Republican": 14,
          "total": 76
        },
        "rights": {
          "Democratic": 187,
          "Republican": 42,
          "total": 229
        }
      }
    },
    {
      "state": "IN",
      "Democratic": 627,
      "Republican": 1020,
      "total": 1647,
      "topic_breakdown": {
        "abortion": {
          "Democratic": 3,
          "Republican": 103,
          "total": 106
        },
        "capitol": {
          "Democratic": 1,
          "Republican": 19,
          "total": 20
        },
        "climate": {
          "Democratic": 37,
          "Republican": 21,
          "total": 58
        },
        "covid": {
          "Democratic": 507,
          "Republican": 756,
          "total": 1263
        },
        "gun": {
          "Democratic": 28,
          "Republican": 33,
          "total": 61
        },
        "immigra": {
          "Democratic": 3,
          "Republican": 41,
          "total": 44
        },
        "rights": {
          "Democratic": 48,
          "Republican": 47,
          "total": 95
        }
      },
      "legislator_breakdown": {
        "abortion": {
          "Democratic": 3,
          "Republican": 103,
          "total": 106
        },
        "capitol": {
          "Democratic": 1,
          "Republican": 19,
          "total": 20
        },
        "climate": {
          "Democratic": 37,
          "Republican": 21,
          "total": 58
        },
        "covid": {
          "Democratic": 507,
          "Republican": 756,
          "total": 1263
        },
        "gun": {
          "Democratic": 28,
          "Republican": 33,
          "total": 61
        },
        "immigra": {
          "Democratic": 3,
          "Republican": 41,
          "total": 44
        },
        "rights": {
          "Democratic": 48,
          "Republican": 47,
          "total": 95
        }
      }
    },
    {
      "state": "KS",
      "Democratic": 1189,
      "Republican": 516,
      "total": 1705,
      "topic_breakdown": {
        "abortion": {
          "Democratic": 134,
          "Republican": 24,
          "total": 158
        },
        "capitol": {
          "Democratic": 26,
          "Republican": 1,
          "total": 27
        },
        "climate": {
          "Democratic": 24,
          "Republican": 6,
          "total": 30
        },
        "covid": {
          "Democratic": 773,
          "Republican": 440,
          "total": 1213
        },
        "gun": {
          "Democratic": 81,
          "Republican": 11,
          "total": 92
        },
        "immigra": {
          "Democratic": 11,
          "Republican": 2,
          "total": 13
        },
        "rights": {
          "Democratic": 140,
          "Republican": 32,
          "total": 172
        }
      },
      "legislator_breakdown": {
        "abortion": {
          "Democratic": 134,
          "Republican": 24,
          "total": 158
        },
        "capitol": {
          "Democratic": 26,
          "Republican": 1,
          "total": 27
        },
        "climate": {
          "Democratic": 24,
          "Republican": 6,
          "total": 30
        },
        "covid": {
          "Democratic": 773,
          "Republican": 440,
          "total": 1213
        },
        "gun": {
          "Democratic": 81,
          "Republican": 11,
          "total": 92
        },
        "immigra": {
          "Democratic": 11,
          "Republican": 2,
          "total": 13
        },
        "rights": {
          "Democratic": 140,
          "Republican": 32,
          "total": 172
        }
      }
    },
    {
      "state": "KY",
      "Democratic": 1643,
      "Republican": 1025,
      "total": 2668,
      "topic_breakdown": {
        "abortion": {
          "Democratic": 92,
          "Republican": 93,
          "total": 185
        },
        "capitol": {
          "Democratic": 89,
          "Republican": 65,
          "total": 154
        },
        "climate": {
          "Democratic": 97,
          "Republican": 5,
          "total": 102
        },
        "covid": {
          "Democratic": 1006,
          "Republican": 675,
          "total": 1681
        },
        "gun": {
          "Democratic": 121,
          "Republican": 37,
          "total": 158
        },
        "immigra": {
          "Democratic": 44,
          "Republican": 13,
          "total": 57
        },
        "rights": {
          "Democratic": 194,
          "Republican": 137,
          "total": 331
        }
      },
      "legislator_breakdown": {
        "abortion": {
          "Democratic": 92,
          "Republican": 93,
          "total": 185
        },
        "capitol": {
          "Democratic": 89,
          "Republican": 65,
          "total": 154
        },
        "climate": {
          "Democratic": 97,
          "Republican": 5,
          "total": 102
        },
        "covid": {
          "Democratic": 1006,
          "Republican": 675,
          "total": 1681
        },
        "gun": {
          "Democratic": 121,
          "Republican": 37,
          "total": 158
        },
        "immigra": {
          "Democratic": 44,
          "Republican": 13,
          "total": 57
        },
        "rights": {
          "Democratic": 194,
          "Republican": 137,
          "total": 331
        }
      }
    },
    {
      "state": "LA",
      "Democratic": 1023,
      "Republican": 342,
      "total": 1365,
      "topic_breakdown": {
        "abortion": {
          "Democratic": 26,
          "Republican": 19,
          "total": 45
        },
        "capitol": {
          "Democratic": 12,
          "Republican": 2,
          "total": 14
        },
        "climate": {
          "Democratic": 40,
          "Republican": 19,
          "total": 59
        },
        "covid": {
          "Democratic": 777,
          "Republican": 240,
          "total": 1017
        },
        "gun": {
          "Democratic": 47,
          "Republican": 24,
          "total": 71
        },
        "immigra": {
          "Democratic": 10,
          "Republican": 9,
          "total": 19
        },
        "rights": {
          "Democratic": 111,
          "Republican": 29,
          "total": 140
        }
      },
      "legislator_breakdown": {
        "abortion": {
          "Democratic": 26,
          "Republican": 19,
          "total": 45
        },
        "capitol": {
          "Democratic": 12,
          "Republican": 2,
          "total": 14
        },
        "climate": {
          "Democratic": 40,
          "Republican": 19,
          "total": 59
        },
        "covid": {
          "Democratic": 777,
          "Republican": 240,
          "total": 1017
        },
        "gun": {
          "Democratic": 47,
          "Republican": 24,
          "total": 71
        },
        "immigra": {
          "Democratic": 10,
          "Republican": 9,
          "total": 19
        },
        "rights": {
          "Democratic": 111,
          "Republican": 29,
          "total": 140
        }
      }
    },
    {
      "state": "MA",
      "Democratic": 15003,
      "Republican": 2019,
      "total": 17022,
      "topic_breakdown": {
        "abortion": {
          "Democratic": 290,
          "Republican": 2,
          "total": 292
        },
        "capitol": {
          "Democratic": 49,
          "Republican": 2,
          "total": 51
        },
        "climate": {
          "Democratic": 1913,
          "Republican": 41,
          "total": 1954
        },
        "covid": {
          "Democratic": 11023,
          "Republican": 1919,
          "total": 12942
        },
        "gun": {
          "Democratic": 322,
          "Republican": 11,
          "total": 333
        },
        "immigra": {
          "Democratic": 574,
          "Republican": 8,
          "total": 582
        },
        "rights": {
          "Democratic": 832,
          "Republican": 36,
          "total": 868
        }
      },
      "legislator_breakdown": {
        "abortion": {
          "Democratic": 290,
          "Republican": 2,
          "total": 292
        },
        "capitol": {
          "Democratic": 49,
          "Republican": 2,
          "total": 51
        },
        "climate": {
          "Democratic": 1913,
          "Republican": 41,
          "total": 1954
        },
        "covid": {
          "Democratic": 11023,
          "Republican": 1919,
          "total": 12942
        },
        "gun": {
          "Democratic": 322,
          "Republican": 11,
          "total": 333
        },
        "immigra": {
          "Democratic": 574,
          "Republican": 8,
          "total": 582
        },
        "rights": {
          "Democratic": 832,
          "Republican": 36,
          "total": 868
        }
      }
    },
    {
      "state": "MD",
      "Democratic": 8291,
      "Republican": 855,
      "total": 9146,
      "topic_breakdown": {
        "abortion": {
          "Democratic": 74,
          "Republican": 19,
          "total": 93
        },
        "capitol": {
          "Democratic": 120,
          "Republican": 16,
          "total": 136
        },
        "climate": {
          "Democratic": 426,
          "Republican": 16,
          "total": 442
        },
        "covid": {
          "Democratic": 6038,
          "Republican": 569,
          "total": 6607
        },
        "gun": {
          "Democratic": 452,
          "Republican": 134,
          "total": 586
        },
        "immigra": {
          "Democratic": 422,
          "Republican": 23,
          "total": 445
        },
        "rights": {
          "Democratic": 759,
          "Republican": 78,
          "total": 837
        }
      },
      "legislator_breakdown": {
        "abortion": {
          "Democratic": 74,
          "Republican": 19,
          "total": 93
        },
        "capitol": {
          "Democratic": 120,
          "Republican": 16,
          "total": 136
        },
        "climate": {
          "Democratic": 426,
          "Republican": 16,
          "total": 442
        },
        "covid": {
          "Democratic": 6038,
          "Republican": 569,
          "total": 6607
        },
        "gun": {
          "Democratic": 452,
          "Republican": 134,
          "total": 586
        },
        "immigra": {
          "Democratic": 422,
          "Republican": 23,
          "total": 445
        },
        "rights": {
          "Democratic": 759,
          "Republican": 78,
          "total": 837
        }
      }
    },
    {
      "state": "ME",
      "Democratic": 1470,
      "Republican": 30,
      "total": 1500,
      "topic_breakdown": {
        "abortion": {
          "Democratic": 25,
          "Republican": 0,
          "total": 25
        },
        "capitol": {
          "Democratic": 34,
          "Republican": 4,
          "total": 38
        },
        "climate": {
          "Democratic": 210,
          "Republican": 2,
          "total": 212
        },
        "covid": {
          "Democratic": 910,
          "Republican": 16,
          "total": 926
        },
        "gun": {
          "Democratic": 59,
          "Republican": 3,
          "total": 62
        },
        "immigra": {
          "Democratic": 20,
          "Republican": 0,
          "total": 20
        },
        "rights": {
          "Democratic": 212,
          "Republican": 5,
          "total": 217
        }
      },
      "legislator_breakdown": {
        "abortion": {
          "Democratic": 25,
          "Republican": 0,
          "total": 25
        },
        "capitol": {
          "Democratic": 34,
          "Republican": 4,
          "total": 38
        },
        "climate": {
          "Democratic": 210,
          "Republican": 2,
          "total": 212
        },
        "covid": {
          "Democratic": 910,
          "Republican": 16,
          "total": 926
        },
        "gun": {
          "Democratic": 59,
          "Republican": 3,
          "total": 62
        },
        "immigra": {
          "Democratic": 20,
          "Republican": 0,
          "total": 20
        },
        "rights": {
          "Democratic": 212,
          "Republican": 5,
          "total": 217
        }
      }
    },
    {
      "state": "MI",
      "Democratic": 4565,
      "Republican": 593,
      "total": 5158,
      "topic_breakdown": {
        "abortion": {
          "Democratic": 94,
          "Republican": 7,
          "total": 101
        },
        "capitol": {
          "Democratic": 163,
          "Republican": 11,
          "total": 174
        },
        "climate": {
          "Democratic": 209,
          "Republican": 22,
          "total": 231
        },
        "covid": {
          "Democratic": 3174,
          "Republican": 472,
          "total": 3646
        },
        "gun": {
          "Democratic": 341,
          "Republican": 33,
          "total": 374
        },
        "immigra": {
          "Democratic": 89,
          "Republican": 6,
          "total": 95
        },
        "rights": {
          "Democratic": 495,
          "Republican": 42,
          "total": 537
        }
      },
      "legislator_breakdown": {
        "abortion": {
          "Democratic": 94,
          "Republican": 7,
          "total": 101
        },
        "capitol": {
          "Democratic": 163,
          "Republican": 11,
          "total": 174
        },
        "climate": {
          "Democratic": 209,
          "Republican": 22,
          "total": 231
        },
        "covid": {
          "Democratic": 3174,
          "Republican": 472,
          "total": 3646
        },
        "gun": {
          "Democratic": 341,
          "Republican": 33,
          "total": 374
        },
        "immigra": {
          "Democratic": 89,
          "Republican": 6,
          "total": 95
        },
        "rights": {
          "Democratic": 495,
          "Republican": 42,
          "total": 537
        }
      }
    },
    {
      "state": "MN",
      "Democratic": 10738,
      "Republican": 1744,
      "total": 12482,
      "topic_breakdown": {
        "abortion": {
          "Democratic": 198,
          "Republican": 27,
          "total": 225
        },
        "capitol": {
          "Democratic": 322,
          "Republican": 43,
          "total": 365
        },
        "climate": {
          "Democratic": 1292,
          "Republican": 41,
          "total": 1333
        },
        "covid": {
          "Democratic": 7292,
          "Republican": 1417,
          "total": 8709
        },
        "gun": {
          "Democratic": 516,
          "Republican": 84,
          "total": 600
        },
        "immigra": {
          "Democratic": 327,
          "Republican": 23,
          "total": 350
        },
        "rights": {
          "Democratic": 791,
          "Republican": 109,
          "total": 900
        }
      },
      "legislator_breakdown": {
        "abortion": {
          "Democratic": 198,
          "Republican": 27,
          "total": 225
        },
        "capitol": {
          "Democratic": 322,
          "Republican": 43,
          "total": 365
        },
        "climate": {
          "Democratic": 1292,
          "Republican": 41,
          "total": 1333
        },
        "covid": {
          "Democratic": 7292,
          "Republican": 1417,
          "total": 8709
        },
        "gun": {
          "Democratic": 516,
          "Republican": 84,
          "total": 600
        },
        "immigra": {
          "Democratic": 327,
          "Republican": 23,
          "total": 350
        },
        "rights": {
          "Democratic": 791,
          "Republican": 109,
          "total": 900
        }
      }
    },
    {
      "state": "MO",
      "Democratic": 4076,
      "Republican": 2451,
      "total": 6527,
      "topic_breakdown": {
        "abortion": {
          "Democratic": 145,
          "Republican": 273,
          "total": 418
        },
        "capitol": {
          "Democratic": 81,
          "Republican": 26,
          "total": 107
        },
        "climate": {
          "Democratic": 40,
          "Republican": 29,
          "total": 69
        },
        "covid": {
          "Democratic": 2994,
          "Republican": 1456,
          "total": 4450
        },
        "gun": {
          "Democratic": 465,
          "Republican": 260,
          "total": 725
        },
        "immigra": {
          "Democratic": 52,
          "Republican": 40,
          "total": 92
        },
        "rights": {
          "Democratic": 299,
          "Republican": 367,
          "total": 666
        }
      },
      "legislator_breakdown": {
        "abortion": {
          "Democratic": 145,
          "Republican": 273,
          "total": 418
        },
        "capitol": {
          "Democratic": 81,
          "Republican": 26,
          "total": 107
        },
        "climate": {
          "Democratic": 40,
          "Republican": 29,
          "total": 69
        },
        "covid": {
          "Democratic": 2994,
          "Republican": 1456,
          "total": 4450
        },
        "gun": {
          "Democratic": 465,
          "Republican": 260,
          "total": 725
        },
        "immigra": {
          "Democratic": 52,
          "Republican": 40,
          "total": 92
        },
        "rights": {
          "Democratic": 299,
          "Republican": 367,
          "total": 666
        }
      }
    },
    {
      "state": "MS",
      "Democratic": 413,
      "Republican": 415,
      "total": 828,
      "topic_breakdown": {
        "abortion": {
          "Democratic": 2,
          "Republican": 7,
          "total": 9
        },
        "capitol": {
          "Democratic": 13,
          "Republican": 12,
          "total": 25
        },
        "covid": {
          "Democratic": 339,
          "Republican": 334,
          "total": 673
        },
        "gun": {
          "Democratic": 13,
          "Republican": 33,
          "total": 46
        },
        "immigra": {
          "Democratic": 5,
          "Republican": 3,
          "total": 8
        },
        "rights": {
          "Democratic": 41,
          "Republican": 25,
          "total": 66
        },
        "climate": {
          "Democratic": 0,
          "Republican": 1,
          "total": 1
        }
      },
      "legislator_breakdown": {
        "abortion": {
          "Democratic": 2,
          "Republican": 7,
          "total": 9
        },
        "capitol": {
          "Democratic": 13,
          "Republican": 12,
          "total": 25
        },
        "covid": {
          "Democratic": 339,
          "Republican": 334,
          "total": 673
        },
        "gun": {
          "Democratic": 13,
          "Republican": 33,
          "total": 46
        },
        "immigra": {
          "Democratic": 5,
          "Republican": 3,
          "total": 8
        },
        "rights": {
          "Democratic": 41,
          "Republican": 25,
          "total": 66
        },
        "climate": {
          "Democratic": 0,
          "Republican": 1,
          "total": 1
        }
      }
    },
    {
      "state": "MT",
      "Democratic": 1075,
      "Republican": 139,
      "total": 1214,
      "topic_breakdown": {
        "abortion": {
          "Democratic": 63,
          "Republican": 1,
          "total": 64
        },
        "capitol": {
          "Democratic": 72,
          "Republican": 7,
          "total": 79
        },
        "climate": {
          "Democratic": 101,
          "Republican": 7,
          "total": 108
        },
        "covid": {
          "Democratic": 624,
          "Republican": 87,
          "total": 711
        },
        "gun": {
          "Democratic": 75,
          "Republican": 18,
          "total": 93
        },
        "immigra": {
          "Democratic": 11,
          "Republican": 1,
          "total": 12
        },
        "rights": {
          "Democratic": 129,
          "Republican": 18,
          "total": 147
        }
      },
      "legislator_breakdown": {
        "abortion": {
          "Democratic": 63,
          "Republican": 1,
          "total": 64
        },
        "capitol": {
          "Democratic": 72,
          "Republican": 7,
          "total": 79
        },
        "climate": {
          "Democratic": 101,
          "Republican": 7,
          "total": 108
        },
        "covid": {
          "Democratic": 624,
          "Republican": 87,
          "total": 711
        },
        "gun": {
          "Democratic": 75,
          "Republican": 18,
          "total": 93
        },
        "immigra": {
          "Democratic": 11,
          "Republican": 1,
          "total": 12
        },
        "rights": {
          "Democratic": 129,
          "Republican": 18,
          "total": 147
        }
      }
    },
    {
      "state": "NC",
      "Democratic": 5672,
      "Republican": 1150,
      "total": 6822,
      "topic_breakdown": {
        "abortion": {
          "Democratic": 89,
          "Republican": 8,
          "total": 97
        },
        "capitol": {
          "Democratic": 206,
          "Republican": 11,
          "total": 217
        },
        "climate": {
          "Democratic": 239,
          "Republican": 50,
          "total": 289
        },
        "covid": {
          "Democratic": 4025,
          "Republican": 991,
          "total": 5016
        },
        "gun": {
          "Democratic": 510,
          "Republican": 25,
          "total": 535
        },
        "immigra": {
          "Democratic": 91,
          "Republican": 9,
          "total": 100
        },
        "rights": {
          "Democratic": 512,
          "Republican": 56,
          "total": 568
        }
      },
      "legislator_breakdown": {
        "abortion": {
          "Democratic": 89,
          "Republican": 8,
          "total": 97
        },
        "capitol": {
          "Democratic": 206,
          "Republican": 11,
          "total": 217
        },
        "climate": {
          "Democratic": 239,
          "Republican": 50,
          "total": 289
        },
        "covid": {
          "Democratic": 4025,
          "Republican": 991,
          "total": 5016
        },
        "gun": {
          "Democratic": 510,
          "Republican": 25,
          "total": 535
        },
        "immigra": {
          "Democratic": 91,
          "Republican": 9,
          "total": 100
        },
        "rights": {
          "Democratic": 512,
          "Republican": 56,
          "total": 568
        }
      }
    },
    {
      "state": "ND",
      "Democratic": 852,
      "Republican": 100,
      "total": 952,
      "topic_breakdown": {
        "abortion": {
          "Democratic": 16,
          "Republican": 6,
          "total": 22
        },
        "capitol": {
          "Democratic": 2,
          "Republican": 5,
          "total": 7
        },
        "climate": {
          "Democratic": 6,
          "Republican": 1,
          "total": 7
        },
        "covid": {
          "Democratic": 752,
          "Republican": 78,
          "total": 830
        },
        "gun": {
          "Democratic": 40,
          "Republican": 6,
          "total": 46
        },
        "immigra": {
          "Democratic": 3,
          "Republican": 0,
          "total": 3
        },
        "rights": {
          "Democratic": 33,
          "Republican": 4,
          "total": 37
        }
      },
      "legislator_breakdown": {
        "abortion": {
          "Democratic": 16,
          "Republican": 6,
          "total": 22
        },
        "capitol": {
          "Democratic": 2,
          "Republican": 5,
          "total": 7
        },
        "climate": {
          "Democratic": 6,
          "Republican": 1,
          "total": 7
        },
        "covid": {
          "Democratic": 752,
          "Republican": 78,
          "total": 830
        },
        "gun": {
          "Democratic": 40,
          "Republican": 6,
          "total": 46
        },
        "immigra": {
          "Democratic": 3,
          "Republican": 0,
          "total": 3
        },
        "rights": {
          "Democratic": 33,
          "Republican": 4,
          "total": 37
        }
      }
    },
    {
      "state": "NE",
      "Democratic": 1295,
      "Republican": 11,
      "total": 1306,
      "topic_breakdown": {
        "abortion": {
          "Democratic": 6,
          "Republican": 0,
          "total": 6
        },
        "capitol": {
          "Democratic": 24,
          "Republican": 0,
          "total": 24
        },
        "climate": {
          "Democratic": 22,
          "Republican": 0,
          "total": 22
        },
        "covid": {
          "Democratic": 1070,
          "Republican": 11,
          "total": 1081
        },
        "gun": {
          "Democratic": 28,
          "Republican": 0,
          "total": 28
        },
        "immigra": {
          "Democratic": 37,
          "Republican": 0,
          "total": 37
        },
        "rights": {
          "Democratic": 108,
          "Republican": 0,
          "total": 108
        }
      },
      "legislator_breakdown": {
        "abortion": {
          "Democratic": 6,
          "Republican": 0,
          "total": 6
        },
        "capitol": {
          "Democratic": 24,
          "Republican": 0,
          "total": 24
        },
        "climate": {
          "Democratic": 22,
          "Republican": 0,
          "total": 22
        },
        "covid": {
          "Democratic": 1070,
          "Republican": 11,
          "total": 1081
        },
        "gun": {
          "Democratic": 28,
          "Republican": 0,
          "total": 28
        },
        "immigra": {
          "Democratic": 37,
          "Republican": 0,
          "total": 37
        },
        "rights": {
          "Democratic": 108,
          "Republican": 0,
          "total": 108
        }
      }
    },
    {
      "state": "NH",
      "Democratic": 11414,
      "Republican": 1213,
      "total": 12627,
      "topic_breakdown": {
        "abortion": {
          "Democratic": 654,
          "Republican": 210,
          "total": 864
        },
        "capitol": {
          "Democratic": 609,
          "Republican": 33,
          "total": 642
        },
        "climate": {
          "Democratic": 784,
          "Republican": 39,
          "total": 823
        },
        "covid": {
          "Democratic": 7133,
          "Republican": 586,
          "total": 7719
        },
        "gun": {
          "Democratic": 745,
          "Republican": 164,
          "total": 909
        },
        "immigra": {
          "Democratic": 302,
          "Republican": 66,
          "total": 368
        },
        "rights": {
          "Democratic": 1187,
          "Republican": 115,
          "total": 1302
        }
      },
      "legislator_breakdown": {
        "abortion": {
          "Democratic": 654,
          "Republican": 210,
          "total": 864
        },
        "capitol": {
          "Democratic": 609,
          "Republican": 33,
          "total": 642
        },
        "climate": {
          "Democratic": 784,
          "Republican": 39,
          "total": 823
        },
        "covid": {
          "Democratic": 7133,
          "Republican": 586,
          "total": 7719
        },
        "gun": {
          "Democratic": 745,
          "Republican": 164,
          "total": 909
        },
        "immigra": {
          "Democratic": 302,
          "Republican": 66,
          "total": 368
        },
        "rights": {
          "Democratic": 1187,
          "Republican": 115,
          "total": 1302
        }
      }
    },
    {
      "state": "NJ",
      "Democratic": 1890,
      "Republican": 759,
      "total": 2649,
      "topic_breakdown": {
        "abortion": {
          "Democratic": 10,
          "Republican": 1,
          "total": 11
        },
        "capitol": {
          "Democratic": 11,
          "Republican": 1,
          "total": 12
        },
        "climate": {
          "Democratic": 44,
          "Republican": 5,
          "total": 49
        },
        "covid": {
          "Democratic": 1520,
          "Republican": 675,
          "total": 2195
        },
        "gun": {
          "Democratic": 64,
          "Republican": 18,
          "total": 82
        },
        "immigra": {
          "Democratic": 48,
          "Republican": 13,
          "total": 61
        },
        "rights": {
          "Democratic": 193,
          "Republican": 46,
          "total": 239
        }
      },
      "legislator_breakdown": {
        "abortion": {
          "Democratic": 10,
          "Republican": 1,
          "total": 11
        },
        "capitol": {
          "Democratic": 11,
          "Republican": 1,
          "total": 12
        },
        "climate": {
          "Democratic": 44,
          "Republican": 5,
          "total": 49
        },
        "covid": {
          "Democratic": 1520,
          "Republican": 675,
          "total": 2195
        },
        "gun": {
          "Democratic": 64,
          "Republican": 18,
          "total": 82
        },
        "immigra": {
          "Democratic": 48,
          "Republican": 13,
          "total": 61
        },
        "rights": {
          "Democratic": 193,
          "Republican": 46,
          "total": 239
        }
      }
    },
    {
      "state": "NM",
      "Democratic": 7745,
      "Republican": 145,
      "total": 7890,
      "topic_breakdown": {
        "abortion": {
          "Democratic": 251,
          "Republican": 11,
          "total": 262
        },
        "capitol": {
          "Democratic": 577,
          "Republican": 1,
          "total": 578
        },
        "climate": {
          "Democratic": 489,
          "Republican": 0,
          "total": 489
        },
        "covid": {
          "Democratic": 4982,
          "Republican": 74,
          "total": 5056
        },
        "gun": {
          "Democratic": 572,
          "Republican": 32,
          "total": 604
        },
        "immigra": {
          "Democratic": 255,
          "Republican": 1,
          "total": 256
        },
        "rights": {
          "Democratic": 619,
          "Republican": 26,
          "total": 645
        }
      },
      "legislator_breakdown": {
        "abortion": {
          "Democratic": 251,
          "Republican": 11,
          "total": 262
        },
        "capitol": {
          "Democratic": 577,
          "Republican": 1,
          "total": 578
        },
        "climate": {
          "Democratic": 489,
          "Republican": 0,
          "total": 489
        },
        "covid": {
          "Democratic": 4982,
          "Republican": 74,
          "total": 5056
        },
        "gun": {
          "Democratic": 572,
          "Republican": 32,
          "total": 604
        },
        "immigra": {
          "Democratic": 255,
          "Republican": 1,
          "total": 256
        },
        "rights": {
          "Democratic": 619,
          "Republican": 26,
          "total": 645
        }
      }
    },
    {
      "state": "NV",
      "Democratic": 1968,
      "Republican": 334,
      "total": 2302,
      "topic_breakdown": {
        "abortion": {
          "Democratic": 41,
          "Republican": 2,
          "total": 43
        },
        "capitol": {
          "Democratic": 137,
          "Republican": 6,
          "total": 143
        },
        "climate": {
          "Democratic": 95,
          "Republican": 4,
          "total": 99
        },
        "covid": {
          "Democratic": 1178,
          "Republican": 250,
          "total": 1428
        },
        "gun": {
          "Democratic": 84,
          "Republican": 31,
          "total": 115
        },
        "immigra": {
          "Democratic": 147,
          "Republican": 2,
          "total": 149
        },
        "rights": {
          "Democratic": 286,
          "Republican": 39,
          "total": 325
        }
      },
      "legislator_breakdown": {
        "abortion": {
          "Democratic": 41,
          "Republican": 2,
          "total": 43
        },
        "capitol": {
          "Democratic": 137,
          "Republican": 6,
          "total": 143
        },
        "climate": {
          "Democratic": 95,
          "Republican": 4,
          "total": 99
        },
        "covid": {
          "Democratic": 1178,
          "Republican": 250,
          "total": 1428
        },
        "gun": {
          "Democratic": 84,
          "Republican": 31,
          "total": 115
        },
        "immigra": {
          "Democratic": 147,
          "Republican": 2,
          "total": 149
        },
        "rights": {
          "Democratic": 286,
          "Republican": 39,
          "total": 325
        }
      }
    },
    {
      "state": "NY",
      "Democratic": 16376,
      "Republican": 2492,
      "total": 18868,
      "topic_breakdown": {
        "abortion": {
          "Democratic": 239,
          "Republican": 8,
          "total": 247
        },
        "capitol": {
          "Democratic": 170,
          "Republican": 31,
          "total": 201
        },
        "climate": {
          "Democratic": 926,
          "Republican": 76,
          "total": 1002
        },
        "covid": {
          "Democratic": 11297,
          "Republican": 2045,
          "total": 13342
        },
        "gun": {
          "Democratic": 834,
          "Republican": 115,
          "total": 949
        },
        "immigra": {
          "Democratic": 1155,
          "Republican": 138,
          "total": 1293
        },
        "rights": {
          "Democratic": 1755,
          "Republican": 79,
          "total": 1834
        }
      },
      "legislator_breakdown": {
        "abortion": {
          "Democratic": 239,
          "Republican": 8,
          "total": 247
        },
        "capitol": {
          "Democratic": 170,
          "Republican": 31,
          "total": 201
        },
        "climate": {
          "Democratic": 926,
          "Republican": 76,
          "total": 1002
        },
        "covid": {
          "Democratic": 11297,
          "Republican": 2045,
          "total": 13342
        },
        "gun": {
          "Democratic": 834,
          "Republican": 115,
          "total": 949
        },
        "immigra": {
          "Democratic": 1155,
          "Republican": 138,
          "total": 1293
        },
        "rights": {
          "Democratic": 1755,
          "Republican": 79,
          "total": 1834
        }
      }
    },
    {
      "state": "OH",
      "Democratic": 2184,
      "Republican": 868,
      "total": 3052,
      "topic_breakdown": {
        "abortion": {
          "Democratic": 67,
          "Republican": 26,
          "total": 93
        },
        "capitol": {
          "Democratic": 36,
          "Republican": 11,
          "total": 47
        },
        "climate": {
          "Democratic": 31,
          "Republican": 14,
          "total": 45
        },
        "covid": {
          "Democratic": 1582,
          "Republican": 666,
          "total": 2248
        },
        "gun": {
          "Democratic": 227,
          "Republican": 51,
          "total": 278
        },
        "immigra": {
          "Democratic": 20,
          "Republican": 16,
          "total": 36
        },
        "rights": {
          "Democratic": 221,
          "Republican": 84,
          "total": 305
        }
      },
      "legislator_breakdown": {
        "abortion": {
          "Democratic": 67,
          "Republican": 26,
          "total": 93
        },
        "capitol": {
          "Democratic": 36,
          "Republican": 11,
          "total": 47
        },
        "climate": {
          "Democratic": 31,
          "Republican": 14,
          "total": 45
        },
        "covid": {
          "Democratic": 1582,
          "Republican": 666,
          "total": 2248
        },
        "gun": {
          "Democratic": 227,
          "Republican": 51,
          "total": 278
        },
        "immigra": {
          "Democratic": 20,
          "Republican": 16,
          "total": 36
        },
        "rights": {
          "Democratic": 221,
          "Republican": 84,
          "total": 305
        }
      }
    },
    {
      "state": "OK",
      "Democratic": 2366,
      "Republican": 1135,
      "total": 3501,
      "topic_breakdown": {
        "abortion": {
          "Democratic": 54,
          "Republican": 33,
          "total": 87
        },
        "capitol": {
          "Democratic": 93,
          "Republican": 23,
          "total": 116
        },
        "climate": {
          "Democratic": 18,
          "Republican": 6,
          "total": 24
        },
        "covid": {
          "Democratic": 1894,
          "Republican": 636,
          "total": 2530
        },
        "gun": {
          "Democratic": 113,
          "Republican": 60,
          "total": 173
        },
        "immigra": {
          "Democratic": 20,
          "Republican": 16,
          "total": 36
        },
        "rights": {
          "Democratic": 174,
          "Republican": 361,
          "total": 535
        }
      },
      "legislator_breakdown": {
        "abortion": {
          "Democratic": 54,
          "Republican": 33,
          "total": 87
        },
        "capitol": {
          "Democratic": 93,
          "Republican": 23,
          "total": 116
        },
        "climate": {
          "Democratic": 18,
          "Republican": 6,
          "total": 24
        },
        "covid": {
          "Democratic": 1894,
          "Republican": 636,
          "total": 2530
        },
        "gun": {
          "Democratic": 113,
          "Republican": 60,
          "total": 173
        },
        "immigra": {
          "Democratic": 20,
          "Republican": 16,
          "total": 36
        },
        "rights": {
          "Democratic": 174,
          "Republican": 361,
          "total": 535
        }
      }
    },
    {
      "state": "OR",
      "Democratic": 2491,
      "Republican": 1045,
      "total": 3536,
      "topic_breakdown": {
        "abortion": {
          "Democratic": 31,
          "Republican": 36,
          "total": 67
        },
        "capitol": {
          "Democratic": 40,
          "Republican": 15,
          "total": 55
        },
        "climate": {
          "Democratic": 212,
          "Republican": 65,
          "total": 277
        },
        "covid": {
          "Democratic": 1822,
          "Republican": 794,
          "total": 2616
        },
        "gun": {
          "Democratic": 148,
          "Republican": 81,
          "total": 229
        },
        "immigra": {
          "Democratic": 40,
          "Republican": 23,
          "total": 63
        },
        "rights": {
          "Democratic": 198,
          "Republican": 31,
          "total": 229
        }
      },
      "legislator_breakdown": {
        "abortion": {
          "Democratic": 31,
          "Republican": 36,
          "total": 67
        },
        "capitol": {
          "Democratic": 40,
          "Republican": 15,
          "total": 55
        },
        "climate": {
          "Democratic": 212,
          "Republican": 65,
          "total": 277
        },
        "covid": {
          "Democratic": 1822,
          "Republican": 794,
          "total": 2616
        },
        "gun": {
          "Democratic": 148,
          "Republican": 81,
          "total": 229
        },
        "immigra": {
          "Democratic": 40,
          "Republican": 23,
          "total": 63
        },
        "rights": {
          "Democratic": 198,
          "Republican": 31,
          "total": 229
        }
      }
    },
    {
      "state": "PA",
      "Democratic": 11749,
      "Republican": 4386,
      "total": 16135,
      "topic_breakdown": {
        "abortion": {
          "Democratic": 149,
          "Republican": 20,
          "total": 169
        },
        "capitol": {
          "Democratic": 372,
          "Republican": 31,
          "total": 403
        },
        "climate": {
          "Democratic": 254,
          "Republican": 22,
          "total": 276
        },
        "covid": {
          "Democratic": 9444,
          "Republican": 3886,
          "total": 13330
        },
        "gun": {
          "Democratic": 673,
          "Republican": 119,
          "total": 792
        },
        "immigra": {
          "Democratic": 129,
          "Republican": 8,
          "total": 137
        },
        "rights": {
          "Democratic": 728,
          "Republican": 300,
          "total": 1028
        }
      },
      "legislator_breakdown": {
        "abortion": {
          "Democratic": 149,
          "Republican": 20,
          "total": 169
        },
        "capitol": {
          "Democratic": 372,
          "Republican": 31,
          "total": 403
        },
        "climate": {
          "Democratic": 254,
          "Republican": 22,
          "total": 276
        },
        "covid": {
          "Democratic": 9444,
          "Republican": 3886,
          "total": 13330
        },
        "gun": {
          "Democratic": 673,
          "Republican": 119,
          "total": 792
        },
        "immigra": {
          "Democratic": 129,
          "Republican": 8,
          "total": 137
        },
        "rights": {
          "Democratic": 728,
          "Republican": 300,
          "total": 1028
        }
      }
    },
    {
      "state": "RI",
      "Democratic": 3568,
      "Republican": 1152,
      "total": 4720,
      "topic_breakdown": {
        "abortion": {
          "Democratic": 130,
          "Republican": 16,
          "total": 146
        },
        "capitol": {
          "Democratic": 98,
          "Republican": 35,
          "total": 133
        },
        "climate": {
          "Democratic": 451,
          "Republican": 126,
          "total": 577
        },
        "covid": {
          "Democratic": 1774,
          "Republican": 649,
          "total": 2423
        },
        "gun": {
          "Democratic": 828,
          "Republican": 86,
          "total": 914
        },
        "immigra": {
          "Democratic": 79,
          "Republican": 125,
          "total": 204
        },
        "rights": {
          "Democratic": 208,
          "Republican": 115,
          "total": 323
        }
      },
      "legislator_breakdown": {
        "abortion": {
          "Democratic": 130,
          "Republican": 16,
          "total": 146
        },
        "capitol": {
          "Democratic": 98,
          "Republican": 35,
          "total": 133
        },
        "climate": {
          "Democratic": 451,
          "Republican": 126,
          "total": 577
        },
        "covid": {
          "Democratic": 1774,
          "Republican": 649,
          "total": 2423
        },
        "gun": {
          "Democratic": 828,
          "Republican": 86,
          "total": 914
        },
        "immigra": {
          "Democratic": 79,
          "Republican": 125,
          "total": 204
        },
        "rights": {
          "Democratic": 208,
          "Republican": 115,
          "total": 323
        }
      }
    },
    {
      "state": "SC",
      "Democratic": 2450,
      "Republican": 1586,
      "total": 4036,
      "topic_breakdown": {
        "abortion": {
          "Democratic": 72,
          "Republican": 31,
          "total": 103
        },
        "capitol": {
          "Democratic": 114,
          "Republican": 24,
          "total": 138
        },
        "climate": {
          "Democratic": 63,
          "Republican": 32,
          "total": 95
        },
        "covid": {
          "Democratic": 1822,
          "Republican": 1347,
          "total": 3169
        },
        "gun": {
          "Democratic": 128,
          "Republican": 57,
          "total": 185
        },
        "immigra": {
          "Democratic": 19,
          "Republican": 19,
          "total": 38
        },
        "rights": {
          "Democratic": 232,
          "Republican": 76,
          "total": 308
        }
      },
      "legislator_breakdown": {
        "abortion": {
          "Democratic": 72,
          "Republican": 31,
          "total": 103
        },
        "capitol": {
          "Democratic": 114,
          "Republican": 24,
          "total": 138
        },
        "climate": {
          "Democratic": 63,
          "Republican": 32,
          "total": 95
        },
        "covid": {
          "Democratic": 1822,
          "Republican": 1347,
          "total": 3169
        },
        "gun": {
          "Democratic": 128,
          "Republican": 57,
          "total": 185
        },
        "immigra": {
          "Democratic": 19,
          "Republican": 19,
          "total": 38
        },
        "rights": {
          "Democratic": 232,
          "Republican": 76,
          "total": 308
        }
      }
    },
    {
      "state": "SD",
      "Democratic": 353,
      "Republican": 189,
      "total": 542,
      "topic_breakdown": {
        "abortion": {
          "Democratic": 8,
          "Republican": 20,
          "total": 28
        },
        "capitol": {
          "Democratic": 19,
          "Republican": 0,
          "total": 19
        },
        "climate": {
          "Democratic": 5,
          "Republican": 2,
          "total": 7
        },
        "covid": {
          "Democratic": 263,
          "Republican": 123,
          "total": 386
        },
        "gun": {
          "Democratic": 26,
          "Republican": 13,
          "total": 39
        },
        "immigra": {
          "Democratic": 9,
          "Republican": 1,
          "total": 10
        },
        "rights": {
          "Democratic": 23,
          "Republican": 30,
          "total": 53
        }
      },
      "legislator_breakdown": {
        "abortion": {
          "Democratic": 8,
          "Republican": 20,
          "total": 28
        },
        "capitol": {
          "Democratic": 19,
          "Republican": 0,
          "total": 19
        },
        "climate": {
          "Democratic": 5,
          "Republican": 2,
          "total": 7
        },
        "covid": {
          "Democratic": 263,
          "Republican": 123,
          "total": 386
        },
        "gun": {
          "Democratic": 26,
          "Republican": 13,
          "total": 39
        },
        "immigra": {
          "Democratic": 9,
          "Republican": 1,
          "total": 10
        },
        "rights": {
          "Democratic": 23,
          "Republican": 30,
          "total": 53
        }
      }
    },
    {
      "state": "TN",
      "Democratic": 3674,
      "Republican": 2163,
      "total": 5837,
      "topic_breakdown": {
        "abortion": {
          "Democratic": 102,
          "Republican": 92,
          "total": 194
        },
        "capitol": {
          "Democratic": 243,
          "Republican": 35,
          "total": 278
        },
        "climate": {
          "Democratic": 51,
          "Republican": 35,
          "total": 86
        },
        "covid": {
          "Democratic": 2613,
          "Republican": 1561,
          "total": 4174
        },
        "gun": {
          "Democratic": 268,
          "Republican": 194,
          "total": 462
        },
        "immigra": {
          "Democratic": 48,
          "Republican": 32,
          "total": 80
        },
        "rights": {
          "Democratic": 349,
          "Republican": 214,
          "total": 563
        }
      },
      "legislator_breakdown": {
        "abortion": {
          "Democratic": 102,
          "Republican": 92,
          "total": 194
        },
        "capitol": {
          "Democratic": 243,
          "Republican": 35,
          "total": 278
        },
        "climate": {
          "Democratic": 51,
          "Republican": 35,
          "total": 86
        },
        "covid": {
          "Democratic": 2613,
          "Republican": 1561,
          "total": 4174
        },
        "gun": {
          "Democratic": 268,
          "Republican": 194,
          "total": 462
        },
        "immigra": {
          "Democratic": 48,
          "Republican": 32,
          "total": 80
        },
        "rights": {
          "Democratic": 349,
          "Republican": 214,
          "total": 563
        }
      }
    },
    {
      "state": "TX",
      "Democratic": 13995,
      "Republican": 6456,
      "total": 20451,
      "topic_breakdown": {
        "abortion": {
          "Democratic": 414,
          "Republican": 274,
          "total": 688
        },
        "capitol": {
          "Democratic": 152,
          "Republican": 74,
          "total": 226
        },
        "climate": {
          "Democratic": 349,
          "Republican": 52,
          "total": 401
        },
        "covid": {
          "Democratic": 9717,
          "Republican": 5131,
          "total": 14848
        },
        "gun": {
          "Democratic": 700,
          "Republican": 314,
          "total": 1014
        },
        "immigra": {
          "Democratic": 502,
          "Republican": 133,
          "total": 635
        },
        "rights": {
          "Democratic": 2161,
          "Republican": 478,
          "total": 2639
        }
      },
      "legislator_breakdown": {
        "abortion": {
          "Democratic": 414,
          "Republican": 274,
          "total": 688
        },
        "capitol": {
          "Democratic": 152,
          "Republican": 74,
          "total": 226
        },
        "climate": {
          "Democratic": 349,
          "Republican": 52,
          "total": 401
        },
        "covid": {
          "Democratic": 9717,
          "Republican": 5131,
          "total": 14848
        },
        "gun": {
          "Democratic": 700,
          "Republican": 314,
          "total": 1014
        },
        "immigra": {
          "Democratic": 502,
          "Republican": 133,
          "total": 635
        },
        "rights": {
          "Democratic": 2161,
          "Republican": 478,
          "total": 2639
        }
      }
    },
    {
      "state": "UT",
      "Democratic": 1902,
      "Republican": 801,
      "total": 2703,
      "topic_breakdown": {
        "abortion": {
          "Democratic": 67,
          "Republican": 9,
          "total": 76
        },
        "capitol": {
          "Democratic": 26,
          "Republican": 13,
          "total": 39
        },
        "climate": {
          "Democratic": 79,
          "Republican": 12,
          "total": 91
        },
        "covid": {
          "Democratic": 1444,
          "Republican": 691,
          "total": 2135
        },
        "gun": {
          "Democratic": 89,
          "Republican": 22,
          "total": 111
        },
        "immigra": {
          "Democratic": 59,
          "Republican": 15,
          "total": 74
        },
        "rights": {
          "Democratic": 138,
          "Republican": 39,
          "total": 177
        }
      },
      "legislator_breakdown": {
        "abortion": {
          "Democratic": 67,
          "Republican": 9,
          "total": 76
        },
        "capitol": {
          "Democratic": 26,
          "Republican": 13,
          "total": 39
        },
        "climate": {
          "Democratic": 79,
          "Republican": 12,
          "total": 91
        },
        "covid": {
          "Democratic": 1444,
          "Republican": 691,
          "total": 2135
        },
        "gun": {
          "Democratic": 89,
          "Republican": 22,
          "total": 111
        },
        "immigra": {
          "Democratic": 59,
          "Republican": 15,
          "total": 74
        },
        "rights": {
          "Democratic": 138,
          "Republican": 39,
          "total": 177
        }
      }
    },
    {
      "state": "VA",
      "Democratic": 8351,
      "Republican": 662,
      "total": 9013,
      "topic_breakdown": {
        "abortion": {
          "Democratic": 181,
          "Republican": 21,
          "total": 202
        },
        "capitol": {
          "Democratic": 123,
          "Republican": 31,
          "total": 154
        },
        "climate": {
          "Democratic": 361,
          "Republican": 13,
          "total": 374
        },
        "covid": {
          "Democratic": 4868,
          "Republican": 370,
          "total": 5238
        },
        "gun": {
          "Democratic": 1104,
          "Republican": 102,
          "total": 1206
        },
        "immigra": {
          "Democratic": 237,
          "Republican": 17,
          "total": 254
        },
        "rights": {
          "Democratic": 1477,
          "Republican": 108,
          "total": 1585
        }
      },
      "legislator_breakdown": {
        "abortion": {
          "Democratic": 181,
          "Republican": 21,
          "total": 202
        },
        "capitol": {
          "Democratic": 123,
          "Republican": 31,
          "total": 154
        },
        "climate": {
          "Democratic": 361,
          "Republican": 13,
          "total": 374
        },
        "covid": {
          "Democratic": 4868,
          "Republican": 370,
          "total": 5238
        },
        "gun": {
          "Democratic": 1104,
          "Republican": 102,
          "total": 1206
        },
        "immigra": {
          "Democratic": 237,
          "Republican": 17,
          "total": 254
        },
        "rights": {
          "Democratic": 1477,
          "Republican": 108,
          "total": 1585
        }
      }
    },
    {
      "state": "VT",
      "Democratic": 1638,
      "Republican": 51,
      "total": 1689,
      "topic_breakdown": {
        "abortion": {
          "Democratic": 16,
          "Republican": 0,
          "total": 16
        },
        "capitol": {
          "Democratic": 11,
          "Republican": 0,
          "total": 11
        },
        "climate": {
          "Democratic": 96,
          "Republican": 0,
          "total": 96
        },
        "covid": {
          "Democratic": 1396,
          "Republican": 48,
          "total": 1444
        },
        "gun": {
          "Democratic": 39,
          "Republican": 0,
          "total": 39
        },
        "immigra": {
          "Democratic": 12,
          "Republican": 0,
          "total": 12
        },
        "rights": {
          "Democratic": 68,
          "Republican": 3,
          "total": 71
        }
      },
      "legislator_breakdown": {
        "abortion": {
          "Democratic": 16,
          "Republican": 0,
          "total": 16
        },
        "capitol": {
          "Democratic": 11,
          "Republican": 0,
          "total": 11
        },
        "climate": {
          "Democratic": 96,
          "Republican": 0,
          "total": 96
        },
        "covid": {
          "Democratic": 1396,
          "Republican": 48,
          "total": 1444
        },
        "gun": {
          "Democratic": 39,
          "Republican": 0,
          "total": 39
        },
        "immigra": {
          "Democratic": 12,
          "Republican": 0,
          "total": 12
        },
        "rights": {
          "Democratic": 68,
          "Republican": 3,
          "total": 71
        }
      }
    },
    {
      "state": "WA",
      "Democratic": 3020,
      "Republican": 308,
      "total": 3328,
      "topic_breakdown": {
        "abortion": {
          "Democratic": 43,
          "Republican": 0,
          "total": 43
        },
        "capitol": {
          "Democratic": 45,
          "Republican": 17,
          "total": 62
        },
        "climate": {
          "Democratic": 704,
          "Republican": 16,
          "total": 720
        },
        "covid": {
          "Democratic": 1671,
          "Republican": 219,
          "total": 1890
        },
        "gun": {
          "Democratic": 225,
          "Republican": 17,
          "total": 242
        },
        "immigra": {
          "Democratic": 57,
          "Republican": 9,
          "total": 66
        },
        "rights": {
          "Democratic": 275,
          "Republican": 30,
          "total": 305
        }
      },
      "legislator_breakdown": {
        "abortion": {
          "Democratic": 43,
          "Republican": 0,
          "total": 43
        },
        "capitol": {
          "Democratic": 45,
          "Republican": 17,
          "total": 62
        },
        "climate": {
          "Democratic": 704,
          "Republican": 16,
          "total": 720
        },
        "covid": {
          "Democratic": 1671,
          "Republican": 219,
          "total": 1890
        },
        "gun": {
          "Democratic": 225,
          "Republican": 17,
          "total": 242
        },
        "immigra": {
          "Democratic": 57,
          "Republican": 9,
          "total": 66
        },
        "rights": {
          "Democratic": 275,
          "Republican": 30,
          "total": 305
        }
      }
    },
    {
      "state": "WI",
      "Democratic": 2779,
      "Republican": 1009,
      "total": 3788,
      "topic_breakdown": {
        "abortion": {
          "Democratic": 51,
          "Republican": 19,
          "total": 70
        },
        "capitol": {
          "Democratic": 62,
          "Republican": 34,
          "total": 96
        },
        "climate": {
          "Democratic": 132,
          "Republican": 13,
          "total": 145
        },
        "covid": {
          "Democratic": 2139,
          "Republican": 805,
          "total": 2944
        },
        "gun": {
          "Democratic": 120,
          "Republican": 38,
          "total": 158
        },
        "immigra": {
          "Democratic": 40,
          "Republican": 25,
          "total": 65
        },
        "rights": {
          "Democratic": 235,
          "Republican": 75,
          "total": 310
        }
      },
      "legislator_breakdown": {
        "abortion": {
          "Democratic": 51,
          "Republican": 19,
          "total": 70
        },
        "capitol": {
          "Democratic": 62,
          "Republican": 34,
          "total": 96
        },
        "climate": {
          "Democratic": 132,
          "Republican": 13,
          "total": 145
        },
        "covid": {
          "Democratic": 2139,
          "Republican": 805,
          "total": 2944
        },
        "gun": {
          "Democratic": 120,
          "Republican": 38,
          "total": 158
        },
        "immigra": {
          "Democratic": 40,
          "Republican": 25,
          "total": 65
        },
        "rights": {
          "Democratic": 235,
          "Republican": 75,
          "total": 310
        }
      }
    },
    {
      "state": "WV",
      "Democratic": 504,
      "Republican": 824,
      "total": 1328,
      "topic_breakdown": {
        "abortion": {
          "Democratic": 8,
          "Republican": 15,
          "total": 23
        },
        "capitol": {
          "Democratic": 43,
          "Republican": 17,
          "total": 60
        },
        "climate": {
          "Democratic": 11,
          "Republican": 15,
          "total": 26
        },
        "covid": {
          "Democratic": 394,
          "Republican": 588,
          "total": 982
        },
        "gun": {
          "Democratic": 13,
          "Republican": 58,
          "total": 71
        },
        "immigra": {
          "Democratic": 2,
          "Republican": 12,
          "total": 14
        },
        "rights": {
          "Democratic": 33,
          "Republican": 119,
          "total": 152
        }
      },
      "legislator_breakdown": {
        "abortion": {
          "Democratic": 8,
          "Republican": 15,
          "total": 23
        },
        "capitol": {
          "Democratic": 43,
          "Republican": 17,
          "total": 60
        },
        "climate": {
          "Democratic": 11,
          "Republican": 15,
          "total": 26
        },
        "covid": {
          "Democratic": 394,
          "Republican": 588,
          "total": 982
        },
        "gun": {
          "Democratic": 13,
          "Republican": 58,
          "total": 71
        },
        "immigra": {
          "Democratic": 2,
          "Republican": 12,
          "total": 14
        },
        "rights": {
          "Democratic": 33,
          "Republican": 119,
          "total": 152
        }
      }
    },
    {
      "state": "WY",
      "Democratic": 75,
      "Republican": 223,
      "total": 298,
      "topic_breakdown": {
        "abortion": {
          "Democratic": 3,
          "Republican": 13,
          "total": 16
        },
        "capitol": {
          "Democratic": 1,
          "Republican": 6,
          "total": 7
        },
        "climate": {
          "Democratic": 8,
          "Republican": 4,
          "total": 12
        },
        "covid": {
          "Democratic": 55,
          "Republican": 122,
          "total": 177
        },
        "gun": {
          "Democratic": 5,
          "Republican": 38,
          "total": 43
        },
        "immigra": {
          "Democratic": 1,
          "Republican": 4,
          "total": 5
        },
        "rights": {
          "Democratic": 2,
          "Republican": 36,
          "total": 38
        }
      },
      "legislator_breakdown": {
        "abortion": {
          "Democratic": 3,
          "Republican": 13,
          "total": 16
        },
        "capitol": {
          "Democratic": 1,
          "Republican": 6,
          "total": 7
        },
        "climate": {
          "Democratic": 8,
          "Republican": 4,
          "total": 12
        },
        "covid": {
          "Democratic": 55,
          "Republican": 122,
          "total": 177
        },
        "gun": {
          "Democratic": 5,
          "Republican": 38,
          "total": 43
        },
        "immigra": {
          "Democratic": 1,
          "Republican": 4,
          "total": 5
        },
        "rights": {
          "Democratic": 2,
          "Republican": 36,
          "total": 38
        }
      }
    }
  ]